test/__init__.py
test/module1.py
sometestpackage-0.1.0.dist-info/METADATA
sometestpackage-0.1.0.dist-info/WHEEL
sometestpackage-0.1.0.dist-info/top_level.txt
sometestpackage-0.1.0.dist-info/RECORD
