Metadata-Version: 2.1
Name: sometestpackage
Version: 0.1.0
Summary: Describe your package in one sentence
Home-page: https://github.com/you/your_package
Author: You
Author-email: you@email.com
License: Apache License 2.0
Platform: UNKNOWN
Requires-Dist: flask
